[
    {
        "levelID": -2,
        "levelDrawPath": "..\\data\\floorplans\\placeholder2.jpg",
        "levelCameras": [
            {
                "cameraID": "..\\data\\videos\\4.mp4",
                "cameraLocation": "Dining",
                "cameraCoordinates": [
                    297,
                    295
                ],
                "cameraAngle": 240,
                "cameraColor": [
                    255,
                    85,
                    127
                ],
                "cameraSize": 20
            }
        ]
    },
    {
        "levelID": -1,
        "levelDrawPath": "..\\data\\floorplans\\placeholder5.png",
        "levelCameras": [
            {
                "cameraID": "..\\data\\videos\\0 - Copy.mp4",
                "cameraLocation": "Living Room",
                "cameraCoordinates": [
                    106,
                    340
                ],
                "cameraAngle": 120,
                "cameraColor": [
                    170,
                    255,
                    255
                ],
                "cameraSize": 20
            }
        ]
    },
    {
        "levelID": 0,
        "levelDrawPath": "..\\data\\floorplans\\placeholder1.jpg",
        "levelCameras": [
            {
                "cameraID": "0",
                "cameraLocation": "Utility Closet",
                "cameraCoordinates": [
                    28,
                    363
                ],
                "cameraAngle": 120,
                "cameraColor": [
                    85,
                    0,
                    255
                ],
                "cameraSize": 12
            }
        ]
    },
    {
        "levelID": 1,
        "levelDrawPath": "..\\data\\floorplans\\placeholder3.jpg",
        "levelCameras": [
            {
                "cameraID": "..\\data\\videos\\0000000 - Copy.mp4",
                "cameraLocation": "Study",
                "cameraCoordinates": [
                    386,
                    398
                ],
                "cameraAngle": 240,
                "cameraColor": [
                    255,
                    85,
                    0
                ],
                "cameraSize": 20
            }
        ]
    }
]